LICENSE
MANIFEST.in
README.rst
setup.py
pake/__init__.py
pake/arguments.py
pake/conf.py
pake/filehelper.py
pake/graph.py
pake/pake.py
pake/process.py
pake/program.py
pake/returncodes.py
pake/subpake.py
pake/util.py
pake/entry_points/__init__.py
pake/entry_points/pake_command.py
python_pake.egg-info/PKG-INFO
python_pake.egg-info/SOURCES.txt
python_pake.egg-info/dependency_links.txt
python_pake.egg-info/entry_points.txt
python_pake.egg-info/top_level.txt
tests/integration/__init__.py
tests/integration/test_pakefile.py
tests/unit/__init__.py
tests/unit/assert_stdin_define_values.py
tests/unit/assert_subpake_depth.py
tests/unit/assert_sync_output.py
tests/unit/exit_0.py
tests/unit/exit_10.py
tests/unit/killself.py
tests/unit/returncode_pakefile.py
tests/unit/test_change_detect.py
tests/unit/test_filehelper.py
tests/unit/test_graph.py
tests/unit/test_multitask_exceptions.py
tests/unit/test_pake.py
tests/unit/test_pake_task_exceptions.py
tests/unit/test_process.py
tests/unit/test_program.py
tests/unit/test_show_header.py
tests/unit/test_stdin_defines.py
tests/unit/test_subpake.py
tests/unit/test_subprocessexception.py
tests/unit/test_sync_output.py
tests/unit/test_taskcontext_process.py
tests/unit/test_taskgraph.py
tests/unit/test_util.py
tests/unit/throw.py
tests/unit/timeout.py