Metadata-Version: 1.1
Name: python-pake
Version: 0.17.0.3a1
Summary: A make-like build utility entirely in python.
Home-page: https://github.com/Teriks/pake
Author: Teriks
Author-email: Teriks@users.noreply.github.com
License: BSD 3-Clause
Platform: UNKNOWN
Classifier: Development Status :: 3 - Alpha
Classifier: License :: OSI Approved :: BSD License
Classifier: Intended Audience :: Developers
Classifier: Natural Language :: English
Classifier: Operating System :: OS Independent
Classifier: Programming Language :: Python :: 3.5
Classifier: Topic :: Software Development :: Build Tools
Classifier: Topic :: Utilities
